pyEQL/__init__.py
pyEQL/activity_correction.py
pyEQL/engines.py
pyEQL/equilibrium.py
pyEQL/functions.py
pyEQL/py.typed
pyEQL/salt_ion_match.py
pyEQL/solute.py
pyEQL/solution.py
pyEQL/utils.py
pyEQL/database/geothermal.dat
pyEQL/database/llnl.dat
pyEQL/database/phreeqc_license.txt
pyEQL/database/pyeql_db.json
pyEQL/presets/Ringers lactate.yaml
pyEQL/presets/normal saline.yaml
pyEQL/presets/rainwater.yaml
pyEQL/presets/seawater.yaml
pyEQL/presets/urine.yaml
pyEQL/presets/wastewater.yaml
pyeql-1.3.2.dist-info/licenses/AUTHORS.md
pyeql-1.3.2.dist-info/licenses/LICENSE.txt
pyeql-1.3.2.dist-info/METADATA
pyeql-1.3.2.dist-info/WHEEL
pyeql-1.3.2.dist-info/top_level.txt
pyeql-1.3.2.dist-info/RECORD
