Metadata-Version: 2.4
Name: pyEQL
Version: 1.3.2
Summary: A python interface for solution chemistry
Author-email: Ryan Kingsbury <kingsbury@princeton.edu>
License-Expression: LGPL-3.0-or-later
Project-URL: Docs, https://pyeql.readthedocs.io/
Project-URL: Repo, https://github.com/KingsburyLab/pyEQL
Project-URL: Package, https://pypi.org/project/pyEQL
Classifier: Programming Language :: Python :: 3
Classifier: Programming Language :: Python :: 3.10
Classifier: Programming Language :: Python :: 3.11
Classifier: Programming Language :: Python :: 3.12
Classifier: Development Status :: 4 - Beta
Classifier: Intended Audience :: Science/Research
Classifier: Operating System :: OS Independent
Classifier: Topic :: Scientific/Engineering
Requires-Python: >=3.10
License-File: LICENSE.txt
License-File: AUTHORS.md
Requires-Dist: pint>=0.24.4
Requires-Dist: numpy>1.26
Requires-Dist: scipy>=1.12
Requires-Dist: pymatgen>=2025.1.9
Requires-Dist: iapws>=1.5.3
Requires-Dist: monty>=2024.12.10
Requires-Dist: maggma>=0.71.4
Requires-Dist: phreeqpython>=1.5.2
Provides-Extra: testing
Requires-Dist: setuptools>=68; extra == "testing"
Requires-Dist: pre-commit>=2; extra == "testing"
Requires-Dist: pytest>=7; extra == "testing"
Requires-Dist: pytest-cov>=2.11; extra == "testing"
Requires-Dist: pytest-xdist>2; extra == "testing"
Requires-Dist: black; extra == "testing"
Requires-Dist: mypy>1; extra == "testing"
Requires-Dist: ruff>0.0.100; extra == "testing"
Requires-Dist: tox<4; extra == "testing"
Provides-Extra: docs
Requires-Dist: sphinx>=3.2.1; extra == "docs"
Requires-Dist: sphinx-rtd-theme; extra == "docs"
Requires-Dist: myst-parser[linkify]; extra == "docs"
Provides-Extra: full
Requires-Dist: rich; extra == "full"
Dynamic: license-file
